imdbscraper/__init__.py
imdbscraper/imdb/__init__.py
imdbscraper/imdb/name.py
imdbscraper/tests/__init__.py
imdbscraper/tests/test_imdb_name_biography.py
imdbscraper/tests/test_name.py
imdbscraper-0.1.1.dist-info/WHEEL
imdbscraper-0.1.1.dist-info/METADATA
imdbscraper-0.1.1.dist-info/RECORD
